[
    {
        "Company Name": "Microsoft",
        "Market Cap": "$3.084 T",
        "Price": "$415.10"
    },
    {
        "Company Name": "Apple",
        "Market Cap": "$2.642 T",
        "Price": "$171.13"
    },
    {
        "Company Name": "NVIDIA",
        "Market Cap": "$2.272 T",
        "Price": "$908.88"
    },
    {
        "Company Name": "Saudi Aramco",
        "Market Cap": "$2.046 T",
        "Price": "$8.46"
    },
    {
        "Company Name": "Amazon",
        "Market Cap": "$1.833 T",
        "Price": "$176.56"
    },
    {
        "Company Name": "Alphabet (Google)",
        "Market Cap": "$1.743 T",
        "Price": "$140.77"
    },
    {
        "Company Name": "Meta Platforms (Facebook)",
        "Market Cap": "$1.263 T",
        "Price": "$495.57"
    },
    {
        "Company Name": "Berkshire Hathaway ",
        "Market Cap": "$882.82 B",
        "Price": "$408.13"
    },
    {
        "Company Name": "TSMC",
        "Market Cap": "$737.28 B",
        "Price": "$142.14"
    },
    {
        "Company Name": "Eli Lilly",
        "Market Cap": "$720.07 B",
        "Price": "$757.84"
    },
    {
        "Company Name": "Novo Nordisk",
        "Market Cap": "$595.68 B",
        "Price": "$133.49"
    },
    {
        "Company Name": "Visa",
        "Market Cap": "$585.69 B",
        "Price": "$285.14"
    },
    {
        "Company Name": "Broadcom",
        "Market Cap": "$582.92 B",
        "Price": "$1,258"
    },
    {
        "Company Name": "JPMorgan Chase",
        "Market Cap": "$551.24 B",
        "Price": "$191.38"
    },
    {
        "Company Name": "Tesla",
        "Market Cap": "$539.75 B",
        "Price": "$169.48"
    },
    {
        "Company Name": "Walmart",
        "Market Cap": "$493.47 B",
        "Price": "$61.28"
    },
    {
        "Company Name": "LVMH",
        "Market Cap": "$474.12 B",
        "Price": "$949.11"
    },
    {
        "Company Name": "UnitedHealth",
        "Market Cap": "$449.90 B",
        "Price": "$488.00"
    },
    {
        "Company Name": "Mastercard",
        "Market Cap": "$443.69 B",
        "Price": "$475.61"
    },
    {
        "Company Name": "Exxon Mobil",
        "Market Cap": "$434.59 B",
        "Price": "$109.53"
    },
    {
        "Company Name": "Johnson & Johnson",
        "Market Cap": "$388.05 B",
        "Price": "$161.10"
    },
    {
        "Company Name": "ASML",
        "Market Cap": "$384.84 B",
        "Price": "$968.78"
    },
    {
        "Company Name": "Procter & Gamble",
        "Market Cap": "$381.89 B",
        "Price": "$162.30"
    },
    {
        "Company Name": "Home Depot",
        "Market Cap": "$377.19 B",
        "Price": "$378.99"
    },
    {
        "Company Name": "Samsung",
        "Market Cap": "$376.46 B",
        "Price": "$56.42"
    },
    {
        "Company Name": "Tencent",
        "Market Cap": "$350.30 B",
        "Price": "$37.04"
    },
    {
        "Company Name": "Oracle",
        "Market Cap": "$344.99 B",
        "Price": "$125.52"
    },
    {
        "Company Name": "Costco",
        "Market Cap": "$325.65 B",
        "Price": "$734.20"
    },
    {
        "Company Name": "AbbVie",
        "Market Cap": "$317.71 B",
        "Price": "$179.86"
    },
    {
        "Company Name": "AMD",
        "Market Cap": "$314.73 B",
        "Price": "$194.79"
    },
    {
        "Company Name": "Toyota",
        "Market Cap": "$314.39 B",
        "Price": "$232.83"
    },
    {
        "Company Name": "Merck",
        "Market Cap": "$309.38 B",
        "Price": "$122.16"
    },
    {
        "Company Name": "Kweichow Moutai",
        "Market Cap": "$299.86 B",
        "Price": "$238.71"
    },
    {
        "Company Name": "Salesforce",
        "Market Cap": "$295.53 B",
        "Price": "$304.68"
    },
    {
        "Company Name": "Chevron",
        "Market Cap": "$285.81 B",
        "Price": "$153.89"
    },
    {
        "Company Name": "Bank of America ",
        "Market Cap": "$284.69 B",
        "Price": "$36.08"
    },
    {
        "Company Name": "Nestlé",
        "Market Cap": "$284.61 B",
        "Price": "$108.58"
    },
    {
        "Company Name": "Hermès",
        "Market Cap": "$270.22 B",
        "Price": "$2,580"
    },
    {
        "Company Name": "L'Oréal",
        "Market Cap": "$265.81 B",
        "Price": "$497.10"
    },
    {
        "Company Name": "Netflix",
        "Market Cap": "$263.74 B",
        "Price": "$609.45"
    },
    {
        "Company Name": "Coca-Cola",
        "Market Cap": "$263.57 B",
        "Price": "$61.12"
    },
    {
        "Company Name": "Adobe",
        "Market Cap": "$259.55 B",
        "Price": "$573.55"
    },
    {
        "Company Name": "International Holding Company",
        "Market Cap": "$238.60 B",
        "Price": "$108.78"
    },
    {
        "Company Name": "Accenture",
        "Market Cap": "$237.45 B",
        "Price": "$378.72"
    },
    {
        "Company Name": "ICBC",
        "Market Cap": "$237.19 B",
        "Price": "$0.51"
    },
    {
        "Company Name": "Reliance Industries",
        "Market Cap": "$235.28 B",
        "Price": "$34.77"
    },
    {
        "Company Name": "Linde",
        "Market Cap": "$228.69 B",
        "Price": "$474.89"
    },
    {
        "Company Name": "Pepsico",
        "Market Cap": "$227.19 B",
        "Price": "$165.30"
    },
    {
        "Company Name": "Thermo Fisher Scientific",
        "Market Cap": "$226.24 B",
        "Price": "$593.32"
    },
    {
        "Company Name": "SAP",
        "Market Cap": "$225.82 B",
        "Price": "$192.51"
    },
    {
        "Company Name": "Roche",
        "Market Cap": "$220.13 B",
        "Price": "$274.06"
    },
    {
        "Company Name": "PetroChina",
        "Market Cap": "$214.89 B",
        "Price": "$1.22"
    },
    {
        "Company Name": "Shell",
        "Market Cap": "$211.62 B",
        "Price": "$65.71"
    },
    {
        "Company Name": "AstraZeneca",
        "Market Cap": "$209.52 B",
        "Price": "$67.58"
    },
    {
        "Company Name": "Abbott Laboratories",
        "Market Cap": "$208.49 B",
        "Price": "$120.16"
    },
    {
        "Company Name": "Wells Fargo",
        "Market Cap": "$206.84 B",
        "Price": "$57.82"
    },
    {
        "Company Name": "Walt Disney",
        "Market Cap": "$206.35 B",
        "Price": "$112.50"
    },
    {
        "Company Name": "McDonald",
        "Market Cap": "$204.23 B",
        "Price": "$282.86"
    },
    {
        "Company Name": "Novartis",
        "Market Cap": "$202.98 B",
        "Price": "$99.00"
    },
    {
        "Company Name": "Cisco",
        "Market Cap": "$202.90 B",
        "Price": "$50.11"
    },
    {
        "Company Name": "Agricultural Bank of China",
        "Market Cap": "$197.55 B",
        "Price": "$0.58"
    },
    {
        "Company Name": "T-Mobile US",
        "Market Cap": "$194.75 B",
        "Price": "$164.09"
    },
    {
        "Company Name": "Alibaba",
        "Market Cap": "$190.97 B",
        "Price": "$76.39"
    },
    {
        "Company Name": "QUALCOMM",
        "Market Cap": "$188.88 B",
        "Price": "$169.25"
    },
    {
        "Company Name": "Danaher",
        "Market Cap": "$188.88 B",
        "Price": "$255.35"
    },
    {
        "Company Name": "China Mobile",
        "Market Cap": "$188.18 B",
        "Price": "$8.56"
    },
    {
        "Company Name": "General Electric",
        "Market Cap": "$185.19 B",
        "Price": "$170.16"
    },
    {
        "Company Name": "Intuit",
        "Market Cap": "$183.40 B",
        "Price": "$655.07"
    },
    {
        "Company Name": "Intel",
        "Market Cap": "$182.77 B",
        "Price": "$43.23"
    },
    {
        "Company Name": "Tata Consultancy Services",
        "Market Cap": "$182.75 B",
        "Price": "$50.51"
    },
    {
        "Company Name": "IBM",
        "Market Cap": "$180.32 B",
        "Price": "$196.70"
    },
    {
        "Company Name": "Comcast",
        "Market Cap": "$171.90 B",
        "Price": "$43.28"
    },
    {
        "Company Name": "Caterpillar",
        "Market Cap": "$170.54 B",
        "Price": "$341.52"
    },
    {
        "Company Name": "Verizon",
        "Market Cap": "$169.26 B",
        "Price": "$40.26"
    },
    {
        "Company Name": "Applied Materials",
        "Market Cap": "$166.64 B",
        "Price": "$200.56"
    },
    {
        "Company Name": "Pinduoduo",
        "Market Cap": "$162.56 B",
        "Price": "$122.36"
    },
    {
        "Company Name": "Uber",
        "Market Cap": "$162.48 B",
        "Price": "$78.25"
    },
    {
        "Company Name": "Bank of China",
        "Market Cap": "$162.31 B",
        "Price": "$0.61"
    },
    {
        "Company Name": "American Express",
        "Market Cap": "$161.28 B",
        "Price": "$222.81"
    },
    {
        "Company Name": "Dior",
        "Market Cap": "$161.12 B",
        "Price": "$893.07"
    },
    {
        "Company Name": "Pfizer",
        "Market Cap": "$159.35 B",
        "Price": "$28.22"
    },
    {
        "Company Name": "ServiceNow",
        "Market Cap": "$159.26 B",
        "Price": "$776.88"
    },
    {
        "Company Name": "Siemens",
        "Market Cap": "$158.98 B",
        "Price": "$201.27"
    },
    {
        "Company Name": "China Construction Bank",
        "Market Cap": "$158.92 B",
        "Price": "$0.95"
    },
    {
        "Company Name": "TotalEnergies",
        "Market Cap": "$157.72 B",
        "Price": "$67.79"
    },
    {
        "Company Name": "Texas Instruments",
        "Market Cap": "$157.14 B",
        "Price": "$172.68"
    },
    {
        "Company Name": "Nike",
        "Market Cap": "$153.57 B",
        "Price": "$101.36"
    },
    {
        "Company Name": "Union Pacific Corporation",
        "Market Cap": "$151.98 B",
        "Price": "$249.25"
    },
    {
        "Company Name": "Inditex",
        "Market Cap": "$150.92 B",
        "Price": "$24.24"
    },
    {
        "Company Name": "Philip Morris",
        "Market Cap": "$147.98 B",
        "Price": "$95.32"
    },
    {
        "Company Name": "Amgen",
        "Market Cap": "$147.90 B",
        "Price": "$275.99"
    },
    {
        "Company Name": "Morgan Stanley",
        "Market Cap": "$146.11 B",
        "Price": "$89.35"
    },
    {
        "Company Name": "HSBC",
        "Market Cap": "$144.66 B",
        "Price": "$37.99"
    },
    {
        "Company Name": "HDFC Bank",
        "Market Cap": "$144.31 B",
        "Price": "$56.99"
    },
    {
        "Company Name": "BHP Group",
        "Market Cap": "$143.90 B",
        "Price": "$56.87"
    },
    {
        "Company Name": "Royal Bank Of Canada",
        "Market Cap": "$142.91 B",
        "Price": "$101.08"
    },
    {
        "Company Name": "Lowe's Companies",
        "Market Cap": "$142.01 B",
        "Price": "$247.41"
    },
    {
        "Company Name": "ConocoPhillips",
        "Market Cap": "$138.28 B",
        "Price": "$117.55"
    },
    {
        "Company Name": "Airbus",
        "Market Cap": "$137.26 B",
        "Price": "$174.32"
    },
    {
        "Company Name": "Intuitive Surgical",
        "Market Cap": "$135.75 B",
        "Price": "$382.99"
    }
]